bonetex/__init__.py
bonetex/__main__.py
bonetex/utils.py
bonetex/feature/__init__.py
bonetex/feature/latex3.py
bonetex/feature/matrix.py
bonetex/generator/__init__.py
bonetex/generator/compile.py
bonetex/generator/document.py
bonetex/generator/utils.py
bonetex/generator/content/__init__.py
bonetex/generator/content/command.py
bonetex/generator/content/content.py
bonetex/generator/content/section.py
bonetex/generator/environment/__init__.py
bonetex/generator/environment/environment.py
bonetex/generator/environment/figure.py
bonetex/generator/environment/minipage.py
bonetex/generator/environment/sequence.py
bonetex/generator/environment/table.py
bonetex/parser/__init__.py
bonetex/parser/block.py
bonetex/parser/parser_bone.py
bonetex/parser/parser_tex.py
bonetex/server/__init__.py
bonetex/server/parse_block.py
bonetex/server/server.py
bonetex/server/server_preview.py
bonetex/server/server_socket.py
BoneTeX-0.0.3.dist-info/METADATA
BoneTeX-0.0.3.dist-info/WHEEL
BoneTeX-0.0.3.dist-info/entry_points.txt
BoneTeX-0.0.3.dist-info/top_level.txt
BoneTeX-0.0.3.dist-info/RECORD
