Metadata-Version: 2.1
Name: BoneTeX
Version: 0.0.3
Summary: BoneTeX Core是一个自动生成LaTeX代码的辅助库，
Home-page: https://gitee.com/zrr1999/bonetex
Author: 六个骨头
Author-email: 2742392377@qq.com
License: UNKNOWN
Platform: any
Classifier: Programming Language :: Python :: 3
Classifier: License :: OSI Approved :: GNU Lesser General Public License v3 (LGPLv3)
Classifier: Operating System :: OS Independent
Provides-Extra: command
Requires-Dist: typer ; extra == 'command'
Provides-Extra: fastapi
Requires-Dist: fastapi ; extra == 'fastapi'
Requires-Dist: uvicorn (>=0.3.0) ; extra == 'fastapi'
Provides-Extra: figure
Requires-Dist: opencv-python (>=4.2.0.34) ; extra == 'figure'
Provides-Extra: flask
Requires-Dist: flask (>=1.1.1) ; extra == 'flask'
Requires-Dist: apiflask (>=0.3.0) ; extra == 'flask'
Provides-Extra: mustache
Requires-Dist: chevron ; extra == 'mustache'
Provides-Extra: parse
Requires-Dist: pyparsing ; extra == 'parse'
Provides-Extra: table
Requires-Dist: xlrd ; extra == 'table'
